dlnr_lite/__init__.py
dlnr_lite/_corr.py
dlnr_lite/_dlnr.py
dlnr_lite/_extractor.py
dlnr_lite/_feature.py
dlnr_lite/_refinement.py
dlnr_lite/_update.py
dlnr_lite/_utils.py
dlnr_lite/_warp.py
dlnr_lite-0.1.1.dist-info/licenses/LICENSE
dlnr_lite-0.1.1.dist-info/METADATA
dlnr_lite-0.1.1.dist-info/WHEEL
dlnr_lite-0.1.1.dist-info/top_level.txt
dlnr_lite-0.1.1.dist-info/RECORD
