Metadata-Version: 2.4
Name: dlnr_lite
Version: 0.1.1
Summary: Lightweight fork of DLNR with minimal dependencies for inference only
Author-email: Francis Williams <francis@fwilliams.info>
Requires-Python: >=3.9
License-File: LICENSE
Requires-Dist: einops>=0.8.1
Dynamic: license-file
